verysimplemodule_rafael/__init__.py
verysimplemodule_rafael/add.py
verysimplemodule_rafael/subtract.py
verysimplemodule_rafael/extra/__init__.py
verysimplemodule_rafael/extra/divide.py
verysimplemodule_rafael/extra/multiply.py
verysimplemodule_rafael-0.0.5.dist-info/METADATA
verysimplemodule_rafael-0.0.5.dist-info/WHEEL
verysimplemodule_rafael-0.0.5.dist-info/top_level.txt
verysimplemodule_rafael-0.0.5.dist-info/RECORD
