Metadata-Version: 2.1
Name: verysimplemodule_rafael
Version: 0.0.5
Summary: Pacote inicial
Author: rafael
Author-email: rafaell_pi@hotmail.com
Keywords: python,primeiro pacote
Classifier: Development Status :: 3 - Alpha
Classifier: Intended Audience :: Education
Classifier: Programming Language :: Python :: 3
Classifier: Operating System :: OS Independent
Requires-Dist: numpy
